<annotation>
  <folder/>
  <filename>00126.jpg</filename>
  <database/>
  <annotation/>
  <image/>
  <size>
    <height>1024</height>
    <width>1024</width>
    <depth>3</depth>
  </size>
  <segmented/>
  <object>
    <name>dlo</name>
    <pose/>
    <truncated/>
    <difficult/>
    <bndbox>
      <xmin>684.8556701030928</xmin>
      <ymin>375.2886597938144</ymin>
      <xmax>873.5154639175257</xmax>
      <ymax>483.5360824742268</ymax>
    </bndbox>
  </object>
  <object>
    <name>wheel</name>
    <pose/>
    <truncated/>
    <difficult/>
    <bndbox>
      <xmin>545.680412371134</xmin>
      <ymin>585.0824742268042</ymin>
      <xmax>665.7835051546392</xmax>
      <ymax>766.5257731958764</ymax>
    </bndbox>
  </object>
  <object>
    <name>wheel</name>
    <pose/>
    <truncated/>
    <difficult/>
    <bndbox>
      <xmin>935.8865979381444</xmin>
      <ymin>529.9278350515464</ymin>
      <xmax>993.1030927835052</xmax>
      <ymax>678.8969072164948</ymax>
    </bndbox>
  </object>
  <object>
    <name>aero</name>
    <pose/>
    <truncated/>
    <difficult/>
    <bndbox>
      <xmin>667.8453608247423</xmin>
      <ymin>537.659793814433</ymin>
      <xmax>750.8350515463917</xmax>
      <ymax>581.4742268041238</ymax>
    </bndbox>
  </object>
  <object>
    <name>headlamp</name>
    <pose/>
    <truncated/>
    <difficult/>
    <bndbox>
      <xmin>333.8247422680413</xmin>
      <ymin>533.020618556701</ymin>
      <xmax>528.6701030927835</xmax>
      <ymax>603.1237113402062</ymax>
    </bndbox>
  </object>
  <object>
    <name>headlamp</name>
    <pose/>
    <truncated/>
    <difficult/>
    <bndbox>
      <xmin>62.175257731958766</xmin>
      <ymin>506.7319587628866</ymin>
      <xmax>127.12371134020617</xmax>
      <ymax>584.5670103092783</ymax>
    </bndbox>
  </object>
  <object>
    <name>hood</name>
    <pose/>
    <truncated/>
    <difficult/>
    <bndbox>
      <xmin>68.87628865979383</xmin>
      <ymin>456.7319587628866</ymin>
      <xmax>644.1340206185567</xmax>
      <ymax>613.4329896907217</ymax>
    </bndbox>
  </object>
  <object>
    <name>grill</name>
    <pose/>
    <truncated/>
    <difficult/>
    <bndbox>
      <xmin>68.36082474226805</xmin>
      <ymin>590.7525773195877</ymin>
      <xmax>366.8144329896908</xmax>
      <ymax>662.9175257731958</ymax>
    </bndbox>
  </object>
  <object>
    <name>opening</name>
    <pose/>
    <truncated/>
    <difficult/>
    <bndbox>
      <xmin>408.0515463917526</xmin>
      <ymin>684.5670103092783</ymin>
      <xmax>510.1134020618557</xmax>
      <ymax>748.4845360824743</ymax>
    </bndbox>
  </object>
  <object>
    <name>opening</name>
    <pose/>
    <truncated/>
    <difficult/>
    <bndbox>
      <xmin>45.680412371134025</xmin>
      <ymin>652.6082474226804</ymin>
      <xmax>67.84536082474227</xmax>
      <ymax>701.5773195876288</ymax>
    </bndbox>
  </object>
  <object>
    <name>aero</name>
    <pose/>
    <truncated/>
    <difficult/>
    <bndbox>
      <xmin>48.25773195876292</xmin>
      <ymin>658.2783505154639</ymin>
      <xmax>540.0103092783505</xmax>
      <ymax>757.2474226804123</ymax>
    </bndbox>
  </object>
  <object>
    <name>bodysurface</name>
    <pose/>
    <truncated/>
    <difficult/>
    <bndbox>
      <xmin>663.2061855670104</xmin>
      <ymin>458.27835051546396</ymin>
      <xmax>912.1752577319587</xmax>
      <ymax>666.5257731958764</ymax>
    </bndbox>
  </object>
  <object>
    <name>spoiler</name>
    <pose/>
    <truncated/>
    <difficult/>
    <bndbox>
      <xmin>894.6494845360826</xmin>
      <ymin>420.1340206185567</ymin>
      <xmax>981.7628865979382</xmax>
      <ymax>458.27835051546396</ymax>
    </bndbox>
  </object>
  <object>
    <name>opening</name>
    <pose/>
    <truncated/>
    <difficult/>
    <bndbox>
      <xmin>418.8762886597939</xmin>
      <ymin>490.2371134020619</ymin>
      <xmax>552.8969072164949</xmax>
      <ymax>514.979381443299</ymax>
    </bndbox>
  </object>
  <object>
    <name>opening</name>
    <pose/>
    <truncated/>
    <difficult/>
    <bndbox>
      <xmin>190.52577319587635</xmin>
      <ymin>468.07216494845363</ymin>
      <xmax>250.31958762886597</xmax>
      <ymax>502.60824742268045</ymax>
    </bndbox>
  </object>
  <object>
    <name>frontbumper</name>
    <pose/>
    <truncated/>
    <difficult/>
    <bndbox>
      <xmin>49.28865979381442</xmin>
      <ymin>589.2061855670104</ymin>
      <xmax>583.3092783505155</xmax>
      <ymax>760.8556701030928</ymax>
    </bndbox>
  </object>
  <object>
    <name>fender</name>
    <pose/>
    <truncated/>
    <difficult/>
    <bndbox>
      <xmin>864.7525773195878</xmin>
      <ymin>431.9896907216495</ymin>
      <xmax>1002.8969072164948</xmax>
      <ymax>542.2989690721649</ymax>
    </bndbox>
  </object>
  <object>
    <name>fender</name>
    <pose/>
    <truncated/>
    <difficult/>
    <bndbox>
      <xmin>515.7835051546392</xmin>
      <ymin>485.59793814432993</ymin>
      <xmax>702.8969072164948</xmax>
      <ymax>640.2371134020618</ymax>
    </bndbox>
  </object>
  <object>
    <name>coupe</name>
    <pose/>
    <truncated/>
    <difficult/>
    <bndbox>
      <xmin>45.16494845360825</xmin>
      <ymin>345.9072164948454</ymin>
      <xmax>1002.3814432989691</xmax>
      <ymax>784.5670103092783</ymax>
    </bndbox>
  </object>
  <object>
    <name>mirror</name>
    <pose/>
    <truncated/>
    <difficult/>
    <bndbox>
      <xmin>709.0824742268042</xmin>
      <ymin>428.3814432989691</ymin>
      <xmax>810.1134020618556</xmax>
      <ymax>485.08247422680415</ymax>
    </bndbox>
  </object>
  <object>
    <name>mirror</name>
    <pose/>
    <truncated/>
    <difficult/>
    <bndbox>
      <xmin>280.2164948453608</xmin>
      <ymin>408.7938144329897</ymin>
      <xmax>324.03092783505156</xmax>
      <ymax>453.63917525773195</ymax>
    </bndbox>
  </object>
</annotation>
